{
    "now": "2024-07-07T08:46:12.883Z",
    "perfNow": 4719025.8000000715,
    "diagnosticCorrelation": "51aed925-f8ab-4e1e-97de-5069aee011b1",
    "source": "DownloadSupportFiles",
    "environment": {
        "productName": "adf",
        "buildVersion": "1.0.062124.5",
        "environmentType": 3,
        "resourceName": "Project-ADF-CSI",
        "resourceRegion": "centralindia",
        "resourceGroup": "resource_assignment",
        "subscriptionId": "16b1f21d-9603-44ee-b80a-31e049856474",
        "sessionId": "PpRaMUIt/55A2JgFUtuPGU",
        "operationId": "",
        "gitType": "live",
        "loggingKey": "84d5017d-e57e-4d3e-ad88-d284e6917efb"
    },
    "additionalInfo": {
        "selectedResource": "Dataset_for_customer",
        "selectedResourceType": "dataset"
    }
}